uptools/__init__.py
uptools-0.1.8.dist-info/WHEEL
uptools-0.1.8.dist-info/METADATA
uptools-0.1.8.dist-info/RECORD
