Metadata-Version: 2.1
Name: uptools
Version: 0.1.8
Summary: 
Author: Thomas Klijnsma
Author-email: tklijnsm@gmail.com
Requires-Python: >=3.6,<4.0
Classifier: Programming Language :: Python :: 3
Classifier: Programming Language :: Python :: 3.6
Classifier: Programming Language :: Python :: 3.7
Classifier: Programming Language :: Python :: 3.8
Classifier: Programming Language :: Python :: 3.9
Requires-Dist: seutils (>=0,<1)
Requires-Dist: uproot-methods (>=0.9.2,<0.10.0)
Requires-Dist: uproot3 (>=3.14.4,<4.0.0)
